meteoswiss/__init__.py
meteoswiss/__main__.py
meteoswiss/get_all_stations.py
meteoswiss/get_current_condition.py
meteoswiss/get_forecast.py
meteoswiss/misc.py
meteoswiss-0.0.11.dist-info/LICENSE
meteoswiss-0.0.11.dist-info/METADATA
meteoswiss-0.0.11.dist-info/WHEEL
meteoswiss-0.0.11.dist-info/top_level.txt
meteoswiss-0.0.11.dist-info/RECORD
