Metadata-Version: 2.1
Name: meteoswiss
Version: 0.0.11
Summary: Library to get data from meteo swiss
Home-page: https://github.com/websylv/meteoswiss
Author: websylv
Author-email: div@webhu.org
License: MIT
Platform: UNKNOWN
Classifier: Development Status :: 2 - Pre-Alpha
Classifier: License :: OSI Approved :: MIT License
Classifier: Programming Language :: Python :: 3.6
Classifier: Programming Language :: Python :: 3.7
Requires-Dist: beautifulsoup4 (>=4.8.2)
Requires-Dist: geopy (>=1.20.0)
Requires-Dist: pandas (>=0.25.3)
Requires-Dist: requests (>=2.22.0)
